evomdl/__init__.py
evomdl/version.py
evomdl/core/automl.py
evomdl/core/base_model.py
evomdl/core/registry.py
evomdl/io/data_loader.py
evomdl/io/model_loader.py
evomdl/io/model_saver.py
evomdl/models/classification.py
evomdl/models/image.py
evomdl/models/nlp.py
evomdl/models/regression.py
evomdl/preprocessing/cleaner.py
evomdl/preprocessing/encoder.py
evomdl/preprocessing/pipeline.py
evomdl/preprocessing/scaler.py
evomdl/preprocessing/splitter.py
evomdl/utils/config.py
evomdl/utils/device.py
evomdl/utils/logger.py
evomdl-0.1.0.dist-info/METADATA
evomdl-0.1.0.dist-info/WHEEL
evomdl-0.1.0.dist-info/top_level.txt
evomdl-0.1.0.dist-info/RECORD
